{
  "channelSlug": "larry-legend-tv",
  "videos": [
    {
      "urlOrId": "https://www.youtube.com/watch?v=C2T2y2PhhNQ",
      "title": "97 Mins Of The Greatest Larry Bird x 1980's Celtics NBA Finals Performances",
      "tags": [
        "bird",
        "celtics",
        "nba",
        "1980s",
        "finals",
        "championship"
      ],
      "vibeTags": [
        "legendary",
        "classic",
        "cold-blooded"
      ],
      "qualityScore": 95
    },
    {
      "urlOrId": "https://www.youtube.com/watch?v=GzDR364GS4c",
      "title": "50 Larry Bird Plays That Would Break the Internet Today",
      "tags": [
        "bird",
        "celtics",
        "nba",
        "top-50",
        "clutch",
        "passing"
      ],
      "vibeTags": [
        "legendary",
        "iconic",
        "cold-blooded"
      ],
      "qualityScore": 93
    },
    {
      "urlOrId": "https://www.youtube.com/watch?v=grT6RuwUChY",
      "title": "Larry Bird Most Clutch Moments in CELTICS History \u2014 Legends Mix",
      "tags": [
        "bird",
        "celtics",
        "nba",
        "clutch",
        "legends",
        "history"
      ],
      "vibeTags": [
        "clutch",
        "legendary",
        "cold-blooded"
      ],
      "qualityScore": 92
    },
    {
      "urlOrId": "https://www.youtube.com/watch?v=LddwcKtITtU",
      "title": "Larry Bird Hits the First Clutch 3-Pointer in NBA Finals History",
      "tags": [
        "bird",
        "celtics",
        "nba",
        "1981",
        "finals",
        "clutch-three"
      ],
      "vibeTags": [
        "iconic",
        "clutch",
        "legendary"
      ],
      "qualityScore": 92
    },
    {
      "urlOrId": "https://www.youtube.com/watch?v=EcQKvJER8Vs",
      "title": "Larry Bird Highlights | Part 1 | Boston Celtics | NBC Sports Boston",
      "tags": [
        "bird",
        "celtics",
        "nba",
        "highlights",
        "career",
        "nbc"
      ],
      "vibeTags": [
        "classic",
        "legendary",
        "nostalgic"
      ],
      "qualityScore": 90
    }
  ]
}